KWsearch.py
MANIFEST.in
README.rst
setup.py
KWsearch.egg-info/PKG-INFO
KWsearch.egg-info/SOURCES.txt
KWsearch.egg-info/dependency_links.txt
KWsearch.egg-info/top_level.txt
docs/index.html
docs/pic1.png
docs/pic2.png