Metadata-Version: 1.1
Name: KWsearch
Version: 0.0.1
Summary: file cataloging tool
Home-page: https://github.com/vkopey/KWsearch
Author: Volodymyr Kopei
Author-email: vkopey@gmail.com
License: MIT
Keywords: search,cataloging
Platform: UNKNOWN
Classifier: Development Status :: 3 - Alpha
Classifier: License :: OSI Approved :: MIT License
Classifier: Natural Language :: Ukranian
Classifier: Operating System :: Microsoft :: Windows
Classifier: Programming Language :: Python :: 2
Classifier: Programming Language :: Python :: 2.6
Classifier: Programming Language :: Python :: 2.7
